nlp_tools_dataminer/__init__.py
nlp_tools_dataminer/core.py
nlp_tools_dataminer-0.1.1.dist-info/licenses/LICENSE
nlp_tools_dataminer-0.1.1.dist-info/METADATA
nlp_tools_dataminer-0.1.1.dist-info/WHEEL
nlp_tools_dataminer-0.1.1.dist-info/top_level.txt
nlp_tools_dataminer-0.1.1.dist-info/RECORD
